nurgapy/__init__.py
nurgapy/trackbar.py
nurgapy/tyme.py
nurgapy-0.2.0.dist-info/LICENSE
nurgapy-0.2.0.dist-info/METADATA
nurgapy-0.2.0.dist-info/WHEEL
nurgapy-0.2.0.dist-info/RECORD
