Metadata-Version: 2.3
Name: nurgapy
Version: 0.2.0
Summary: This lightweight Python library provides reusable utility functions to simplify common development tasks.
License: MIT
Author: nurgalive
Author-email: github@nurgalive.com
Requires-Python: >=3.12
Classifier: License :: OSI Approved :: MIT License
Classifier: Programming Language :: Python :: 3
Classifier: Programming Language :: Python :: 3.12
Classifier: Programming Language :: Python :: 3.13
